kramersmoyal/__init__.py
kramersmoyal/binning.py
kramersmoyal/kernels.py
kramersmoyal/kmc.py
kramersmoyal-0.4.1.dist-info/LICENSE
kramersmoyal-0.4.1.dist-info/METADATA
kramersmoyal-0.4.1.dist-info/WHEEL
kramersmoyal-0.4.1.dist-info/top_level.txt
kramersmoyal-0.4.1.dist-info/RECORD
