Metadata-Version: 2.1
Name: kramersmoyal
Version: 0.4.1
Summary: Calculate Kramers-Moyal coefficients for stochastic process of any dimension, up to any order.
Home-page: https://github.com/LRydin/KramersMoyal
Author: Leonardo Rydin Gorjão and Francisco Meirinhos
Author-email: leonardo.rydin@gmail.com
Classifier: Programming Language :: Python :: 3
Classifier: License :: OSI Approved :: MIT License
Classifier: Operating System :: OS Independent
Requires-Python: >=3.7
License-File: LICENSE
